face_detector/__init__.py
face_detector/data/shape_predictor_5_face_landmarks.dat
face_detector/data/zlib-1.2.9.tar.gz
face_detector/data/mtcnn/det1.npy
face_detector/data/mtcnn/det2.npy
face_detector/data/mtcnn/det3.npy
face_detector/detector_dlib/__init__.py
face_detector/detector_mtcnn/__init__.py
face_detector/detector_mtcnn/mtcnn_aux.py
face_detector-0.4.data/scripts/facedetector
face_detector-0.4.dist-info/METADATA
face_detector-0.4.dist-info/WHEEL
face_detector-0.4.dist-info/top_level.txt
face_detector-0.4.dist-info/RECORD
