Metadata-Version: 2.1
Name: face-detector
Version: 0.4
Summary: State-of-the-art face detection and landmarks localization
Home-page: https://github.com/roj4s/face_detector
Author: Luis Rojas Aguilera
Author-email: rojas@icomp.ufam.edu.br
License: UNKNOWN
Platform: UNKNOWN
Classifier: Programming Language :: Python :: 3
Classifier: License :: OSI Approved :: MIT License
Classifier: Operating System :: OS Independent
Requires-Dist: absl-py (==0.7.1)
Requires-Dist: astor (==0.7.1)
Requires-Dist: dlib (==19.17.0)
Requires-Dist: gast (==0.2.2)
Requires-Dist: grpcio (==1.19.0)
Requires-Dist: h5py (==2.9.0)
Requires-Dist: Keras-Applications (==1.0.7)
Requires-Dist: Keras-Preprocessing (==1.0.9)
Requires-Dist: Markdown (==3.1)
Requires-Dist: mock (==2.0.0)
Requires-Dist: numpy (==1.16.2)
Requires-Dist: opencv-python (==4.0.0.21)
Requires-Dist: pbr (==5.1.3)
Requires-Dist: protobuf (==3.7.1)
Requires-Dist: six (==1.12.0)
Requires-Dist: tensorboard (==1.13.1)
Requires-Dist: tensorflow (==1.13.1)
Requires-Dist: tensorflow-estimator (==1.13.0)
Requires-Dist: termcolor (==1.1.0)
Requires-Dist: Werkzeug (==0.15.2)
